robloxinfo/__init__.py
robloxinfo/client.py
robloxinfo/exceptions.py
robloxinfo/models.py
robloxinfo-0.1.1.dist-info/licenses/LICENSE
robloxinfo-0.1.1.dist-info/METADATA
robloxinfo-0.1.1.dist-info/WHEEL
robloxinfo-0.1.1.dist-info/top_level.txt
robloxinfo-0.1.1.dist-info/RECORD
